llama_index/embeddings/alibabacloud_aisearch/__init__.py
llama_index/embeddings/alibabacloud_aisearch/base.py
llama_index_embeddings_alibabacloud_aisearch-0.3.1.dist-info/METADATA
llama_index_embeddings_alibabacloud_aisearch-0.3.1.dist-info/WHEEL
llama_index_embeddings_alibabacloud_aisearch-0.3.1.dist-info/licenses/LICENSE
llama_index_embeddings_alibabacloud_aisearch-0.3.1.dist-info/RECORD
